LICENSE
README.md
pyproject.toml
rocrate_validator/__init__.py
rocrate_validator/cli/__init__.py
rocrate_validator/cli/commands/errors.py
rocrate_validator/cli/commands/profiles.py
rocrate_validator/cli/commands/validate.py
rocrate_validator/cli/main.py
rocrate_validator/cli/ui/__init__.py
rocrate_validator/cli/ui/text/__init__.py
rocrate_validator/cli/ui/text/describe.py
rocrate_validator/cli/ui/text/validate.py
rocrate_validator/cli/utils.py
rocrate_validator/constants.py
rocrate_validator/errors.py
rocrate_validator/events.py
rocrate_validator/models.py
rocrate_validator/profiles/process-run-crate/may/0_software-application.ttl
rocrate_validator/profiles/process-run-crate/may/1_create_action.ttl
rocrate_validator/profiles/process-run-crate/may/3_container_image.ttl
rocrate_validator/profiles/process-run-crate/must/1_create_action.ttl
rocrate_validator/profiles/process-run-crate/must/2_root_data_entity_metadata.ttl
rocrate_validator/profiles/process-run-crate/profile.ttl
rocrate_validator/profiles/process-run-crate/should/0_software-application.ttl
rocrate_validator/profiles/process-run-crate/should/1_create_action.ttl
rocrate_validator/profiles/process-run-crate/should/2_collection.ttl
rocrate_validator/profiles/process-run-crate/should/3_container_image.ttl
rocrate_validator/profiles/provenance-run-crate/may/0_computational_workflow.ttl
rocrate_validator/profiles/provenance-run-crate/may/0_tool.ttl
rocrate_validator/profiles/provenance-run-crate/may/1_howtostep.ttl
rocrate_validator/profiles/provenance-run-crate/may/1_tool_action.ttl
rocrate_validator/profiles/provenance-run-crate/may/3_controlaction_organizeaction.ttl
rocrate_validator/profiles/provenance-run-crate/must/0_computational_workflow.ttl
rocrate_validator/profiles/provenance-run-crate/must/0_tool.ttl
rocrate_validator/profiles/provenance-run-crate/must/1_howtostep.ttl
rocrate_validator/profiles/provenance-run-crate/must/1_tool_action.ttl
roc_validator-0.8.0.dist-info/METADATA
roc_validator-0.8.0.dist-info/WHEEL
roc_validator-0.8.0.dist-info/entry_points.txt
roc_validator-0.8.0.dist-info/licenses/LICENSE
roc_validator-0.8.0.dist-info/RECORD
