Metadata-Version: 2.4
Name: roc-validator
Version: 0.8.0
Summary: A Python package to validate RO-Crates
License: Apache-2.0
License-File: LICENSE
Keywords: RO-Crate,validation,metadata,research object,data management,scientific data,Python
Author: Marco Enrico Piras
Author-email: kikkomep@crs4.it
Requires-Python: >=3.10,<4.0
Classifier: Development Status :: 4 - Beta
Classifier: Environment :: Console
Classifier: Intended Audience :: Developers
Classifier: Intended Audience :: Science/Research
Classifier: License :: OSI Approved :: Apache Software License
Classifier: Natural Language :: English
Classifier: Operating System :: MacOS :: MacOS X
Classifier: Operating System :: Microsoft :: Windows
Classifier: Operating System :: POSIX :: Linux
Classifier: Programming Language :: Python :: 3
Classifier: Programming Language :: Python :: 3.10
Classifier: Programming Language :: Python :: 3.11
Classifier: Programming Language :: Python :: 3.12
Classifier: Programming Language :: Python :: 3.13
Classifier: Programming Language :: Python :: 3.14
Classifier: Topic :: Scientific/Engineering
Classifier: Topic :: Software Development :: Libraries :: Python Modules
Classifier: Topic :: Software Development :: Quality Assurance
Classifier: Topic :: Software Development :: Testing
Classifier: Topic :: Utilities
Requires-Dist: click (>=8.2,<9.0)
Requires-Dist: colorlog (>=6.9,<7.0)
Requires-Dist: enum-tools (>=0.12,<0.13)
Requires-Dist: inquirerpy (>=0.3.4,<0.4.0)
Requires-Dist: pyshacl (>=0.26,<0.31)
Requires-Dist: rdflib (>=7.1,<8.0)
Requires-Dist: requests (>=2.32,<3.0)
Requires-Dist: requests-cache (>=1.2,<2.0)
Requires-Dist: rich (>=13.9,<14.0)
Requires-Dist: rich-click (>=1.8,<2.0)
Requires-Dist: toml (>=0.10.2,<1.0)
Requires-Dist: typos (>=1.41.0,<2.0.0)
Project-URL: Documentation, https://github.com/crs4/rocrate-validator
Project-URL: Homepage, https://github.com/crs4/rocrate-validator
Project-URL: Repository, https://github.com/crs4/rocrate-validator
